eastwood_games_downloader/__init__.py
eastwood_games_downloader/__main__.py
eastwood_games_downloader/gui.py
eastwood_games_downloader/main.py
eastwood_games_downloader-0.1.1.dist-info/licenses/LICENSE
eastwood_games_downloader-0.1.1.dist-info/METADATA
eastwood_games_downloader-0.1.1.dist-info/WHEEL
eastwood_games_downloader-0.1.1.dist-info/entry_points.txt
eastwood_games_downloader-0.1.1.dist-info/top_level.txt
eastwood_games_downloader-0.1.1.dist-info/RECORD
